gEcon/__init__.py
gEcon/classes/__init__.py
gEcon/classes/block.py
gEcon/classes/model.py
gEcon/classes/progress_bar.py
gEcon/classes/time_aware_symbol.py
gEcon/classes/transformers.py
gEcon/estimation/__init__.py
gEcon/estimation/compiled_kalman.py
gEcon/estimation/estimate.py
gEcon/estimation/estimation_utilities.py
gEcon/estimation/kalman_filter.py
gEcon/estimation/kalman_smoother.py
gEcon/estimation/pt_filter.py
gEcon/exceptions/__init__.py
gEcon/exceptions/exceptions.py
gEcon/numba_linalg/LAPACK.py
gEcon/numba_linalg/__init__.py
gEcon/numba_linalg/intrinsics.py
gEcon/numba_linalg/overloads.py
gEcon/numba_linalg/utilities.py
gEcon/parser/__init__.py
gEcon/parser/constants.py
gEcon/parser/file_loaders.py
gEcon/parser/gEcon_parser.py
gEcon/parser/parse_distributions.py
gEcon/parser/parse_equations.py
gEcon/parser/parse_plaintext.py
gEcon/parser/validation.py
gEcon/plotting/__init__.py
gEcon/plotting/plotting.py
gEcon/sampling/__init__.py
gEcon/sampling/posterior_utilities.py
gEcon/sampling/prior_utilities.py
gEcon/shared/__init__.py
gEcon/shared/dynare_convert.py
gEcon/shared/statsmodel_convert.py
gEcon/shared/typing.py
gEcon/shared/utilities.py
gEcon/solvers/__init__.py
gEcon/solvers/cycle_reduction.py
gEcon/solvers/gensys.py
gEcon/solvers/perturbation.py
gEcon/solvers/steady_state.py
gEcon.py-1.0.0.dist-info/METADATA
gEcon.py-1.0.0.dist-info/WHEEL
gEcon.py-1.0.0.dist-info/entry_points.txt
gEcon.py-1.0.0.dist-info/top_level.txt
gEcon.py-1.0.0.dist-info/RECORD
