Metadata-Version: 2.1
Name: gEcon.py
Version: 1.0.0
Summary: A package for solving, estimating, and analyzing DSGE models
Home-page: https://github.com/jessegrabowski/gEcon.py
Author: Jesse Grabowski
Author-email: jessegrabowski@gmail.com
Requires-Dist: arviz
Requires-Dist: emcee
Requires-Dist: matplotlib
Requires-Dist: numba
Requires-Dist: numpy
Requires-Dist: pymc
Requires-Dist: pyparsing
Requires-Dist: scipy
Requires-Dist: statsmodels
Requires-Dist: sympy
